nymeria
